{"is_source_file": true, "format": "Dart", "description": "This file defines an API client for a Flutter application, including a singleton class that manages HTTP requests to a backend server. It provides methods for GET, POST, PUT, and DELETE operations, handles authorization tokens via shared preferences, and reads configuration from environment variables or defaults.", "external_files": ["dart:convert", "package:flutter/foundation.dart", "package:flutter_dotenv/flutter_dotenv.dart", "package:http/http.dart", "package:shared_preferences/shared_preferences.dart"], "external_methods": ["dotenv.maybeGet", "const String.fromEnvironment", "SharedPreferences.getInstance", "SharedPreferences.getString", "http.get", "http.post", "http.put", "http.delete", "jsonDecode", "jsonEncode", "debugPrint"], "published": ["ApiClient", "ApiException"], "classes": [{"name": "ApiException", "description": "Custom exception class that encapsulates HTTP error responses, including status code and message."}, {"name": "ApiClient", "description": "Singleton class providing methods for making HTTP requests to the backend API, managing headers, base URL configuration, and response processing."}], "methods": [{"name": "ApiClient()", "description": "Factory constructor that returns the singleton instance of ApiClient."}, {"name": "baseUrl getter", "description": "Determines the base URL for API requests from environment variables, dart-define, or a default fallback."}, {"name": "_headers", "description": "Asynchronously constructs the request headers, including authorization tokens fetched from shared preferences."}, {"name": "_uri", "description": "Constructs a Uri object from a path and optional query parameters, normalizing the URL."}, {"name": "get", "description": "Performs an HTTP GET request to the specified path with optional query parameters."}, {"name": "post", "description": "Performs an HTTP POST request with an optional JSON body."}, {"name": "put", "description": "Performs an HTTP PUT request with an optional JSON body."}, {"name": "delete", "description": "Performs an HTTP DELETE request to the specified path."}, {"name": "_processResponse", "description": "Processes the HTTP response, decoding JSON if successful, or throwing an ApiException if an error occurs."}], "calls": ["dotenv.maybeGet", "SharedPreferences.getInstance", "SharedPreferences.getString", "http.get", "http.post", "http.put", "http.delete", "jsonDecode", "jsonEncode", "debugPrint"], "search-terms": ["ApiClient", "singleton", "HTTP methods", "environment variables", "SharedPreferences token", "dio", "json processing", "API base URL"], "state": 2, "file_id": 20, "knowledge_revision": 48, "git_revision": "", "hash": "d48eb83f6234b56bc4bb5c231a76121e", "format-version": 4, "code-base-name": "expense_frontend", "filename": "expense_frontend/lib/core/api_client.dart", "revision_history": [{"48": ""}]}